example_notebook_scripts_old/Effect_of_training_dataset.ipynb
example_notebook_scripts_old/README.md
example_notebook_scripts_old/Step1_Generation_dataset_LaueNN.ipynb
example_notebook_scripts_old/Step2_Training_LaueNN.ipynb
example_notebook_scripts_old/Step2a_Optimize_architecture_LaueNN.ipynb
example_notebook_scripts_old/Step3_Prediction_LaueNN.ipynb
example_notebook_scripts_old/Step3a_Generate_simulateLPforPrediction_LaueNN.ipynb
example_notebook_scripts_old/__init__.py
example_notebook_scripts_old/average_spots_per_crystal.ipynb
example_notebook_scripts_old/multi_material_LaueNN/README.md
example_notebook_scripts_old/multi_material_LaueNN/__init__.py
example_notebook_scripts_old/multi_material_LaueNN/multi_mat_Prediction_LaueNN_interfaceGUI.py
example_notebook_scripts_old/multi_material_LaueNN/multi_mat_generation_training_LaueNN.py
example_notebook_scripts_old/multi_material_LaueNN/multi_mat_simulatedata_LaueNN.py
example_notebook_scripts_old/multi_material_LaueNN/multi_mat_verifyPrediction_LaueNN.py
example_notebook_scripts_old/py_scripts/Step1_Generation_dataset_LaueNN.py
example_notebook_scripts_old/py_scripts/Step2_Training_LaueNN.py
example_notebook_scripts_old/py_scripts/Step2a_Optimize_architecture_LaueNN.py
example_notebook_scripts_old/py_scripts/Step3_Prediction_LaueNN.py
example_notebook_scripts_old/py_scripts/Step3a_Generate_simulateLPforPrediction_LaueNN.py
example_notebook_scripts_old/py_scripts/__init__.py
example_notebook_scripts_old/py_scripts/check_prediction.py
lauetoolsnn/GUI_multi_mat_LaueNN.py
lauetoolsnn/NNmodels.py
lauetoolsnn/__init__.py
lauetoolsnn/icon.png
lauetoolsnn/lauetoolsneuralnetwork.py
lauetoolsnn/lauetoolsnn.py
lauetoolsnn/lauetoolsnn_logo_bXM_2.png
lauetoolsnn/lauetoolsnn_splash_bXM_2.png
lauetoolsnn/settings.ini
lauetoolsnn/uniform_orientations_2000.npz
lauetoolsnn/utils_lauenn.py
lauetoolsnn/end_to_end_scripts/LaueNN_pyScript_1_or_2phase.ipynb
lauetoolsnn/end_to_end_scripts/LaueNN_pyScript_1_or_2phase.py
lauetoolsnn-3.1.19.dist-info/LICENSE
lauetoolsnn-3.1.19.dist-info/METADATA
lauetoolsnn-3.1.19.dist-info/WHEEL
lauetoolsnn-3.1.19.dist-info/entry_points.txt
lauetoolsnn-3.1.19.dist-info/top_level.txt
lauetoolsnn-3.1.19.dist-info/RECORD
