Metadata-Version: 2.1
Name: lauetoolsnn
Version: 3.1.19
Summary: LaueNN- neural network training and prediction routine to index single and polycrystalline Laue diffraction patterns
Home-page: https://github.com/BM32ESRF/LaueNN
Author: Ravi raj purohit PURUSHOTTAM RAJ PUROHIT
Author-email: purushot@esrf.fr
Classifier: Programming Language :: Python :: 3.7
Classifier: Programming Language :: Python :: 3.8
Classifier: Programming Language :: Python :: 3.9
Classifier: Programming Language :: Python :: 3.10
Classifier: Topic :: Scientific/Engineering :: Physics
Classifier: Intended Audience :: Science/Research
Classifier: Development Status :: 5 - Production/Stable
Classifier: License :: OSI Approved :: MIT License 
Requires-Python: >=3.7,<=3.10.8
License-File: LICENSE
Requires-Dist: matplotlib (>=3.4.2)
Requires-Dist: Keras (<=2.10.0,>=2.7.0)
Requires-Dist: tensorflow (<=2.10.0,>=2.7.0)
Requires-Dist: scipy (>=1.7.0)
Requires-Dist: numpy (<=1.22.0,>=1.18.5)
Requires-Dist: h5py (>=3.1)
Requires-Dist: PyQt5 (>=5.9)
Requires-Dist: scikit-learn (>=0.24.2)
Requires-Dist: fabio (>=0.11.0)
Requires-Dist: networkx (>=2.6.3)
Requires-Dist: scikit-image (>=0.18.0)
Requires-Dist: tqdm (>=4.60.0)
